{"latitude": 29.848893, "longitude": -97.953522, "timezone": "America/Chicago", "currently": {"time": 1564170730, "summary": "Partly Cloudy", "icon": "partly-cloudy-day", "nearestStormDistance": 68, "nearestStormBearing": 168, "precipIntensity": 0, "precipProbability": 0, "temperature": 90.98, "apparentTemperature": 90.98, "dewPoint": 56.06, "humidity": 0.31, "pressure": 1017.8, "windSpeed": 6.38, "windGust": 12.79, "windBearing": 66, "cloudCover": 0.22, "uvIndex": 9, "visibility": 10, "ozone": 292.4}, "minutely": {"summary": "Partly cloudy for the hour.", "icon": "partly-cloudy-day", "data": [{"time": 1564170720, "precipIntensity": 0, "precipProbability": 0}, {"time": 1564170780, "precipIntensity": 0, "precipProbability": 0}, {"time": 1564170840, "precipIntensity": 0, "precipProbability": 0}, {"time": 1564170900, "precipIntensity": 0, "precipProbability": 0}, {"time": 1564170960, "precipIntensity": 0, "precipProbability": 0}, {"time": 1564171020, "precipIntensity": 0, "precipProbability": 0}, {"time": 1564171080, "precipIntensity": 0, "precipProbability": 0}, {"time": 1564171140, "precipIntensity": 0, "precipProbability": 0}, {"time": 1564171200, "precipIntensity": 0, "precipProbability": 0}, {"time": 1564171260, "precipIntensity": 0, "precipProbability": 0}, {"time": 1564171320, "precipIntensity": 0, "precipProbability": 0}, {"time": 1564171380, "precipIntensity": 0, "precipProbability": 0}, {"time": 1564171440, "precipIntensity": 0, "precipProbability": 0}, {"time": 1564171500, "precipIntensity": 0, "precipProbability": 0}, {"time": 1564171560, "precipIntensity": 0, "precipProbability": 0}, {"time": 1564171620, "precipIntensity": 0, "precipProbability": 0}, {"time": 1564171680, "precipIntensity": 0, "precipProbability": 0}, {"time": 1564171740, "precipIntensity": 0, "precipProbability": 0}, {"time": 1564171800, "precipIntensity": 0, "precipProbability": 0}, {"time": 1564171860, "precipIntensity": 0, "precipProbability": 0}, {"time": 1564171920, "precipIntensity": 0, "precipProbability": 0}, {"time": 1564171980, "precipIntensity": 0, "precipProbability": 0}, {"time": 1564172040, "precipIntensity": 0, "precipProbability": 0}, {"time": 1564172100, "precipIntensity": 0, "precipProbability": 0}, {"time": 1564172160, "precipIntensity": 0, "precipProbability": 0}, {"time": 1564172220, "precipIntensity": 0, "precipProbability": 0}, {"time": 1564172280, "precipIntensity": 0, "precipProbability": 0}, {"time": 1564172340, "precipIntensity": 0, "precipProbability": 0}, {"time": 1564172400, "precipIntensity": 0, "precipProbability": 0}, {"time": 1564172460, "precipIntensity": 0, "precipProbability": 0}, {"time": 1564172520, "precipIntensity": 0, "precipProbability": 0}, {"time": 1564172580, "precipIntensity": 0, "precipProbability": 0}, {"time": 1564172640, "precipIntensity": 0, "precipProbability": 0}, {"time": 1564172700, "precipIntensity": 0, "precipProbability": 0}, {"time": 1564172760, "precipIntensity": 0, "precipProbability": 0}, {"time": 1564172820, "precipIntensity": 0, "precipProbability": 0}, {"time": 1564172880, "precipIntensity": 0, "precipProbability": 0}, {"time": 1564172940, "precipIntensity": 0, "precipProbability": 0}, {"time": 1564173000, "precipIntensity": 0, "precipProbability": 0}, {"time": 1564173060, "precipIntensity": 0, "precipProbability": 0}, {"time": 1564173120, "precipIntensity": 0, "precipProbability": 0}, {"time": 1564173180, "precipIntensity": 0, "precipProbability": 0}, {"time": 1564173240, "precipIntensity": 0, "precipProbability": 0}, {"time": 1564173300, "precipIntensity": 0, "precipProbability": 0}, {"time": 1564173360, "precipIntensity": 0, "precipProbability": 0}, {"time": 1564173420, "precipIntensity": 0, "precipProbability": 0}, {"time": 1564173480, "precipIntensity": 0, "precipProbability": 0}, {"time": 1564173540, "precipIntensity": 0, "precipProbability": 0}, {"time": 1564173600, "precipIntensity": 0, "precipProbability": 0}, {"time": 1564173660, "precipIntensity": 0, "precipProbability": 0}, {"time": 1564173720, "precipIntensity": 0, "precipProbability": 0}, {"time": 1564173780, "precipIntensity": 0, "precipProbability": 0}, {"time": 1564173840, "precipIntensity": 0, "precipProbability": 0}, {"time": 1564173900, "precipIntensity": 0, "precipProbability": 0}, {"time": 1564173960, "precipIntensity": 0, "precipProbability": 0}, {"time": 1564174020, "precipIntensity": 0, "precipProbability": 0}, {"time": 1564174080, "precipIntensity": 0, "precipProbability": 0}, {"time": 1564174140, "precipIntensity": 0, "precipProbability": 0}, {"time": 1564174200, "precipIntensity": 0, "precipProbability": 0}, {"time": 1564174260, "precipIntensity": 0, "precipProbability": 0}, {"time": 1564174320, "precipIntensity": 0, "precipProbability": 0}]}, "hourly": {"summary": "Partly cloudy throughout the day.", "icon": "clear-day", "data": [{"time": 1564167600, "summary": "Partly Cloudy", "icon": "partly-cloudy-day", "precipIntensity": 0, "precipProbability": 0, "temperature": 89.19, "apparentTemperature": 89.19, "dewPoint": 56.87, "humidity": 0.34, "pressure": 1018.52, "windSpeed": 5.89, "windGust": 12.28, "windBearing": 60, "cloudCover": 0.19, "uvIndex": 10, "visibility": 10, "ozone": 293}, {"time": 1564171200, "summary": "Partly Cloudy", "icon": "partly-cloudy-day", "precipIntensity": 0, "precipProbability": 0, "temperature": 91.25, "apparentTemperature": 91.25, "dewPoint": 55.93, "humidity": 0.3, "pressure": 1017.69, "windSpeed": 6.46, "windGust": 12.87, "windBearing": 67, "cloudCover": 0.22, "uvIndex": 9, "visibility": 10, "ozone": 292.3}, {"time": 1564174800, "summary": "Partly Cloudy", "icon": "partly-cloudy-day", "precipIntensity": 0, "precipProbability": 0, "temperature": 92.69, "apparentTemperature": 92.69, "dewPoint": 55.01, "humidity": 0.28, "pressure": 1017.13, "windSpeed": 6.31, "windGust": 12.25, "windBearing": 71, "cloudCover": 0.23, "uvIndex": 7, "visibility": 10, "ozone": 291.7}, {"time": 1564178400, "summary": "Partly Cloudy", "icon": "partly-cloudy-day", "precipIntensity": 0, "precipProbability": 0, "temperature": 93.35, "apparentTemperature": 93.35, "dewPoint": 53.64, "humidity": 0.26, "pressure": 1016.79, "windSpeed": 7.25, "windGust": 10.06, "windBearing": 85, "cloudCover": 0.17, "uvIndex": 5, "visibility": 10, "ozone": 291.4}, {"time": 1564182000, "summary": "Clear", "icon": "clear-day", "precipIntensity": 0, "precipProbability": 0, "temperature": 93.55, "apparentTemperature": 93.55, "dewPoint": 52.82, "humidity": 0.25, "pressure": 1016.61, "windSpeed": 8.08, "windGust": 9.14, "windBearing": 100, "cloudCover": 0.11, "uvIndex": 2, "visibility": 10, "ozone": 291.3}, {"time": 1564185600, "summary": "Clear", "icon": "clear-day", "precipIntensity": 0, "precipProbability": 0, "temperature": 92, "apparentTemperature": 92, "dewPoint": 52.98, "humidity": 0.27, "pressure": 1016.73, "windSpeed": 7.52, "windGust": 8.99, "windBearing": 100, "cloudCover": 0.09, "uvIndex": 1, "visibility": 10, "ozone": 291.1}, {"time": 1564189200, "summary": "Clear", "icon": "clear-day", "precipIntensity": 0, "precipProbability": 0, "temperature": 88.53, "apparentTemperature": 88.53, "dewPoint": 53.66, "humidity": 0.31, "pressure": 1016.84, "windSpeed": 6.44, "windGust": 8.75, "windBearing": 98, "cloudCover": 0.09, "uvIndex": 0, "visibility": 10, "ozone": 290.6}, {"time": 1564192800, "summary": "Partly Cloudy", "icon": "partly-cloudy-night", "precipIntensity": 0, "precipProbability": 0, "temperature": 84.41, "apparentTemperature": 84.41, "dewPoint": 53.77, "humidity": 0.35, "pressure": 1017.29, "windSpeed": 4.94, "windGust": 7.21, "windBearing": 75, "cloudCover": 0.13, "uvIndex": 0, "visibility": 10, "ozone": 290.1}, {"time": 1564196400, "summary": "Partly Cloudy", "icon": "partly-cloudy-night", "precipIntensity": 0, "precipProbability": 0, "temperature": 80.93, "apparentTemperature": 80.93, "dewPoint": 54.31, "humidity": 0.4, "pressure": 1017.53, "windSpeed": 4.61, "windGust": 8.02, "windBearing": 82, "cloudCover": 0.24, "uvIndex": 0, "visibility": 10, "ozone": 289.6}, {"time": 1564200000, "summary": "Partly Cloudy", "icon": "partly-cloudy-night", "precipIntensity": 0, "precipProbability": 0, "temperature": 78.72, "apparentTemperature": 78.72, "dewPoint": 55.5, "humidity": 0.45, "pressure": 1017.85, "windSpeed": 4.56, "windGust": 12.06, "windBearing": 110, "cloudCover": 0.28, "uvIndex": 0, "visibility": 10, "ozone": 289.2}, {"time": 1564203600, "summary": "Partly Cloudy", "icon": "partly-cloudy-night", "precipIntensity": 0, "precipProbability": 0, "temperature": 77.05, "apparentTemperature": 77.05, "dewPoint": 57.95, "humidity": 0.52, "pressure": 1018.13, "windSpeed": 4.84, "windGust": 15.5, "windBearing": 122, "cloudCover": 0.38, "uvIndex": 0, "visibility": 10, "ozone": 288.7}, {"time": 1564207200, "summary": "Partly Cloudy", "icon": "partly-cloudy-night", "precipIntensity": 0, "precipProbability": 0, "temperature": 75.64, "apparentTemperature": 75.64, "dewPoint": 59.73, "humidity": 0.58, "pressure": 1018.36, "windSpeed": 4.78, "windGust": 14.43, "windBearing": 135, "cloudCover": 0.23, "uvIndex": 0, "visibility": 10, "ozone": 288.6}, {"time": 1564210800, "summary": "Partly Cloudy", "icon": "partly-cloudy-night", "precipIntensity": 0, "precipProbability": 0, "temperature": 74.11, "apparentTemperature": 74.22, "dewPoint": 61.09, "humidity": 0.64, "pressure": 1018.5, "windSpeed": 3.86, "windGust": 10.88, "windBearing": 141, "cloudCover": 0.24, "uvIndex": 0, "visibility": 10, "ozone": 288.7}, {"time": 1564214400, "summary": "Partly Cloudy", "icon": "partly-cloudy-night", "precipIntensity": 0, "precipProbability": 0, "temperature": 72.77, "apparentTemperature": 72.99, "dewPoint": 62.09, "humidity": 0.69, "pressure": 1018.54, "windSpeed": 2.85, "windGust": 6.43, "windBearing": 246, "cloudCover": 0.37, "uvIndex": 0, "visibility": 10, "ozone": 289.2}, {"time": 1564218000, "summary": "Partly Cloudy", "icon": "partly-cloudy-night", "precipIntensity": 0, "precipProbability": 0, "temperature": 71.77, "apparentTemperature": 72.11, "dewPoint": 62.87, "humidity": 0.74, "pressure": 1018.57, "windSpeed": 2.29, "windGust": 3.16, "windBearing": 261, "cloudCover": 0.19, "uvIndex": 0, "visibility": 10, "ozone": 289.6}, {"time": 1564221600, "summary": "Partly Cloudy", "icon": "partly-cloudy-night", "precipIntensity": 0, "precipProbability": 0, "temperature": 69.15, "apparentTemperature": 69.62, "dewPoint": 63.44, "humidity": 0.82, "pressure": 1018.98, "windSpeed": 1.94, "windGust": 2.01, "windBearing": 193, "cloudCover": 0.23, "uvIndex": 0, "visibility": 10, "ozone": 289.9}, {"time": 1564225200, "summary": "Partly Cloudy", "icon": "partly-cloudy-night", "precipIntensity": 0, "precipProbability": 0, "temperature": 67.88, "apparentTemperature": 68.4, "dewPoint": 63.47, "humidity": 0.86, "pressure": 1019.24, "windSpeed": 2.01, "windGust": 2.43, "windBearing": 19, "cloudCover": 0.2, "uvIndex": 0, "visibility": 10, "ozone": 290.1}, {"time": 1564228800, "summary": "Partly Cloudy", "icon": "partly-cloudy-day", "precipIntensity": 0, "precipProbability": 0, "temperature": 67.78, "apparentTemperature": 68.36, "dewPoint": 63.84, "humidity": 0.87, "pressure": 1019.54, "windSpeed": 2.34, "windGust": 3.37, "windBearing": 353, "cloudCover": 0.17, "uvIndex": 0, "visibility": 10, "ozone": 290.2}, {"time": 1564232400, "summary": "Clear", "icon": "clear-day", "precipIntensity": 0, "precipProbability": 0, "temperature": 70.74, "apparentTemperature": 71.39, "dewPoint": 65.14, "humidity": 0.82, "pressure": 1019.98, "windSpeed": 3.01, "windGust": 4.76, "windBearing": 24, "cloudCover": 0.11, "uvIndex": 0, "visibility": 10, "ozone": 290}, {"time": 1564236000, "summary": "Clear", "icon": "clear-day", "precipIntensity": 0, "precipProbability": 0, "temperature": 76.19, "apparentTemperature": 76.92, "dewPoint": 66.73, "humidity": 0.73, "pressure": 1020.45, "windSpeed": 3.94, "windGust": 6.74, "windBearing": 86, "cloudCover": 0.05, "uvIndex": 2, "visibility": 10, "ozone": 289.6}, {"time": 1564239600, "summary": "Clear", "icon": "clear-day", "precipIntensity": 0, "precipProbability": 0, "temperature": 80.94, "apparentTemperature": 83.52, "dewPoint": 67.48, "humidity": 0.64, "pressure": 1020.65, "windSpeed": 4.78, "windGust": 8.1, "windBearing": 115, "cloudCover": 0.01, "uvIndex": 4, "visibility": 10, "ozone": 289.2}, {"time": 1564243200, "summary": "Clear", "icon": "clear-day", "precipIntensity": 0, "precipProbability": 0, "temperature": 84.57, "apparentTemperature": 87.21, "dewPoint": 66.82, "humidity": 0.55, "pressure": 1020.36, "windSpeed": 5.38, "windGust": 8.05, "windBearing": 120, "cloudCover": 0.01, "uvIndex": 7, "visibility": 10, "ozone": 288.9}, {"time": 1564246800, "summary": "Clear", "icon": "clear-day", "precipIntensity": 0, "precipProbability": 0, "temperature": 87.16, "apparentTemperature": 89.2, "dewPoint": 65.41, "humidity": 0.49, "pressure": 1019.79, "windSpeed": 5.81, "windGust": 7.32, "windBearing": 120, "cloudCover": 0.02, "uvIndex": 10, "visibility": 10, "ozone": 288.6}, {"time": 1564250400, "summary": "Clear", "icon": "clear-day", "precipIntensity": 0, "precipProbability": 0, "temperature": 88.92, "apparentTemperature": 90.37, "dewPoint": 64.11, "humidity": 0.44, "pressure": 1019.13, "windSpeed": 6.01, "windGust": 6.78, "windBearing": 119, "cloudCover": 0.04, "uvIndex": 11, "visibility": 10, "ozone": 288.3}, {"time": 1564254000, "summary": "Clear", "icon": "clear-day", "precipIntensity": 0, "precipProbability": 0, "temperature": 90.32, "apparentTemperature": 91.23, "dewPoint": 62.9, "humidity": 0.4, "pressure": 1018.45, "windSpeed": 5.85, "windGust": 6.64, "windBearing": 122, "cloudCover": 0.08, "uvIndex": 11, "visibility": 10, "ozone": 287.9}, {"time": 1564257600, "summary": "Partly Cloudy", "icon": "partly-cloudy-day", "precipIntensity": 0, "precipProbability": 0, "temperature": 91.68, "apparentTemperature": 92.07, "dewPoint": 61.62, "humidity": 0.37, "pressure": 1017.69, "windSpeed": 5.52, "windGust": 6.67, "windBearing": 123, "cloudCover": 0.13, "uvIndex": 10, "visibility": 10, "ozone": 287.5}, {"time": 1564261200, "summary": "Partly Cloudy", "icon": "partly-cloudy-day", "precipIntensity": 0, "precipProbability": 0, "temperature": 92.58, "apparentTemperature": 92.63, "dewPoint": 60.71, "humidity": 0.35, "pressure": 1016.99, "windSpeed": 5.46, "windGust": 6.9, "windBearing": 125, "cloudCover": 0.17, "uvIndex": 7, "visibility": 10, "ozone": 287.3}, {"time": 1564264800, "summary": "Partly Cloudy", "icon": "partly-cloudy-day", "precipIntensity": 0, "precipProbability": 0, "temperature": 93.19, "apparentTemperature": 93.19, "dewPoint": 60.44, "humidity": 0.34, "pressure": 1016.35, "windSpeed": 5.95, "windGust": 7.16, "windBearing": 129, "cloudCover": 0.18, "uvIndex": 5, "visibility": 10, "ozone": 287.6}, {"time": 1564268400, "summary": "Partly Cloudy", "icon": "partly-cloudy-day", "precipIntensity": 0, "precipProbability": 0, "temperature": 93.94, "apparentTemperature": 94.05, "dewPoint": 60.58, "humidity": 0.33, "pressure": 1015.74, "windSpeed": 6.61, "windGust": 7.64, "windBearing": 131, "cloudCover": 0.17, "uvIndex": 2, "visibility": 10, "ozone": 288.1}, {"time": 1564272000, "summary": "Partly Cloudy", "icon": "partly-cloudy-day", "precipIntensity": 0, "precipProbability": 0, "temperature": 93, "apparentTemperature": 93.22, "dewPoint": 61.01, "humidity": 0.35, "pressure": 1015.45, "windSpeed": 7.14, "windGust": 8.8, "windBearing": 133, "cloudCover": 0.15, "uvIndex": 1, "visibility": 10, "ozone": 288.3}, {"time": 1564275600, "summary": "Clear", "icon": "clear-day", "precipIntensity": 0, "precipProbability": 0, "temperature": 90.15, "apparentTemperature": 90.54, "dewPoint": 61.82, "humidity": 0.39, "pressure": 1015.62, "windSpeed": 7.53, "windGust": 11.4, "windBearing": 129, "cloudCover": 0.12, "uvIndex": 0, "visibility": 10, "ozone": 288.2}, {"time": 1564279200, "summary": "Clear", "icon": "clear-night", "precipIntensity": 0, "precipProbability": 0, "temperature": 86.52, "apparentTemperature": 87.39, "dewPoint": 62.98, "humidity": 0.45, "pressure": 1016.1, "windSpeed": 7.86, "windGust": 14.78, "windBearing": 124, "cloudCover": 0.07, "uvIndex": 0, "visibility": 10, "ozone": 287.8}, {"time": 1564282800, "summary": "Clear", "icon": "clear-night", "precipIntensity": 0, "precipProbability": 0, "temperature": 83.43, "apparentTemperature": 84.93, "dewPoint": 64.28, "humidity": 0.53, "pressure": 1016.51, "windSpeed": 8.09, "windGust": 17.48, "windBearing": 124, "cloudCover": 0.04, "uvIndex": 0, "visibility": 10, "ozone": 287.3}, {"time": 1564286400, "summary": "Clear", "icon": "clear-night", "precipIntensity": 0, "precipProbability": 0, "temperature": 81.19, "apparentTemperature": 83.25, "dewPoint": 65.81, "humidity": 0.6, "pressure": 1016.73, "windSpeed": 8.34, "windGust": 18.94, "windBearing": 134, "cloudCover": 0.03, "uvIndex": 0, "visibility": 10, "ozone": 286.6}, {"time": 1564290000, "summary": "Clear", "icon": "clear-night", "precipIntensity": 0, "precipProbability": 0, "temperature": 79.53, "apparentTemperature": 81.89, "dewPoint": 67.45, "humidity": 0.67, "pressure": 1016.89, "windSpeed": 8.49, "windGust": 19.48, "windBearing": 148, "cloudCover": 0.04, "uvIndex": 0, "visibility": 10, "ozone": 285.9}, {"time": 1564293600, "summary": "Clear", "icon": "clear-night", "precipIntensity": 0, "precipProbability": 0, "temperature": 78.13, "apparentTemperature": 79.08, "dewPoint": 68.84, "humidity": 0.73, "pressure": 1017.05, "windSpeed": 8.18, "windGust": 18.97, "windBearing": 160, "cloudCover": 0.06, "uvIndex": 0, "visibility": 10, "ozone": 285.2}, {"time": 1564297200, "summary": "Clear", "icon": "clear-night", "precipIntensity": 0, "precipProbability": 0, "temperature": 76.96, "apparentTemperature": 78.06, "dewPoint": 69.86, "humidity": 0.79, "pressure": 1017.18, "windSpeed": 7.1, "windGust": 17.06, "windBearing": 166, "cloudCover": 0.11, "uvIndex": 0, "visibility": 10, "ozone": 284.9}, {"time": 1564300800, "summary": "Partly Cloudy", "icon": "partly-cloudy-night", "precipIntensity": 0, "precipProbability": 0, "temperature": 76.01, "apparentTemperature": 77.24, "dewPoint": 70.72, "humidity": 0.84, "pressure": 1017.27, "windSpeed": 5.6, "windGust": 14.24, "windBearing": 168, "cloudCover": 0.18, "uvIndex": 0, "visibility": 10, "ozone": 284.6}, {"time": 1564304400, "summary": "Partly Cloudy", "icon": "partly-cloudy-night", "precipIntensity": 0, "precipProbability": 0, "temperature": 75.12, "apparentTemperature": 76.48, "dewPoint": 71.41, "humidity": 0.88, "pressure": 1017.41, "windSpeed": 4.52, "windGust": 11.86, "windBearing": 169, "cloudCover": 0.24, "uvIndex": 0, "visibility": 10, "ozone": 284.5}, {"time": 1564308000, "summary": "Partly Cloudy", "icon": "partly-cloudy-night", "precipIntensity": 0, "precipProbability": 0, "temperature": 74.25, "apparentTemperature": 75.73, "dewPoint": 71.97, "humidity": 0.93, "pressure": 1017.56, "windSpeed": 4.12, "windGust": 10.25, "windBearing": 164, "cloudCover": 0.27, "uvIndex": 0, "visibility": 10, "ozone": 284.2}, {"time": 1564311600, "summary": "Humid and Partly Cloudy", "icon": "partly-cloudy-night", "precipIntensity": 0, "precipProbability": 0, "temperature": 73.62, "apparentTemperature": 75.18, "dewPoint": 72.37, "humidity": 0.96, "pressure": 1017.74, "windSpeed": 4.11, "windGust": 9.11, "windBearing": 158, "cloudCover": 0.29, "uvIndex": 0, "visibility": 10, "ozone": 283.8}, {"time": 1564315200, "summary": "Humid and Partly Cloudy", "icon": "partly-cloudy-day", "precipIntensity": 0, "precipProbability": 0, "temperature": 73.88, "apparentTemperature": 75.47, "dewPoint": 72.57, "humidity": 0.96, "pressure": 1017.93, "windSpeed": 4.58, "windGust": 8.89, "windBearing": 154, "cloudCover": 0.29, "uvIndex": 0, "visibility": 9.304, "ozone": 283.5}, {"time": 1564318800, "summary": "Humid and Partly Cloudy", "icon": "partly-cloudy-day", "precipIntensity": 0, "precipProbability": 0, "temperature": 75.65, "apparentTemperature": 77.17, "dewPoint": 72.63, "humidity": 0.9, "pressure": 1018.2, "windSpeed": 5.8, "windGust": 10.21, "windBearing": 159, "cloudCover": 0.37, "uvIndex": 0, "visibility": 10, "ozone": 283.5}, {"time": 1564322400, "summary": "Humid and Partly Cloudy", "icon": "partly-cloudy-day", "precipIntensity": 0, "precipProbability": 0, "temperature": 78.79, "apparentTemperature": 81.86, "dewPoint": 72.59, "humidity": 0.81, "pressure": 1018.5, "windSpeed": 7.4, "windGust": 12.38, "windBearing": 168, "cloudCover": 0.47, "uvIndex": 2, "visibility": 10, "ozone": 283.5}, {"time": 1564326000, "summary": "Humid and Partly Cloudy", "icon": "partly-cloudy-day", "precipIntensity": 0.001, "precipProbability": 0.01, "precipType": "rain", "temperature": 82.21, "apparentTemperature": 87.22, "dewPoint": 72.15, "humidity": 0.72, "pressure": 1018.54, "windSpeed": 8.69, "windGust": 13.99, "windBearing": 174, "cloudCover": 0.5, "uvIndex": 4, "visibility": 10, "ozone": 283.6}, {"time": 1564329600, "summary": "Partly Cloudy", "icon": "partly-cloudy-day", "precipIntensity": 0, "precipProbability": 0, "temperature": 85.72, "apparentTemperature": 91.05, "dewPoint": 70.91, "humidity": 0.61, "pressure": 1018.17, "windSpeed": 9.39, "windGust": 14.37, "windBearing": 173, "cloudCover": 0.39, "uvIndex": 6, "visibility": 10, "ozone": 283.7}, {"time": 1564333200, "summary": "Partly Cloudy", "icon": "partly-cloudy-day", "precipIntensity": 0, "precipProbability": 0, "temperature": 89.02, "apparentTemperature": 93.73, "dewPoint": 69.24, "humidity": 0.52, "pressure": 1017.52, "windSpeed": 9.79, "windGust": 14.18, "windBearing": 169, "cloudCover": 0.22, "uvIndex": 9, "visibility": 10, "ozone": 283.8}, {"time": 1564336800, "summary": "Clear", "icon": "clear-day", "precipIntensity": 0, "precipProbability": 0, "temperature": 91.32, "apparentTemperature": 95.37, "dewPoint": 67.86, "humidity": 0.46, "pressure": 1016.82, "windSpeed": 10.1, "windGust": 14.09, "windBearing": 166, "cloudCover": 0.1, "uvIndex": 11, "visibility": 10, "ozone": 283.9}, {"time": 1564340400, "summary": "Partly Cloudy", "icon": "partly-cloudy-day", "precipIntensity": 0, "precipProbability": 0, "temperature": 93.28, "apparentTemperature": 96.93, "dewPoint": 66.87, "humidity": 0.42, "pressure": 1016, "windSpeed": 10.5, "windGust": 14.36, "windBearing": 166, "cloudCover": 0.13, "uvIndex": 11, "visibility": 10, "ozone": 284.3}]}, "daily": {"summary": "No precipitation throughout the week, with high temperatures rising to 97\u00b0F on Monday.", "icon": "clear-day", "data": [{"time": 1564117200, "summary": "Partly cloudy throughout the day.", "icon": "clear-day", "sunriseTime": 1564141726, "sunsetTime": 1564191018, "moonPhase": 0.81, "precipIntensity": 0.0003, "precipIntensityMax": 0.0019, "precipIntensityMaxTime": 1564182000, "precipProbability": 0.01, "precipType": "rain", "temperatureHigh": 93.55, "temperatureHighTime": 1564182000, "temperatureLow": 67.78, "temperatureLowTime": 1564228800, "apparentTemperatureHigh": 93.55, "apparentTemperatureHighTime": 1564182000, "apparentTemperatureLow": 68.36, "apparentTemperatureLowTime": 1564228800, "dewPoint": 57.45, "humidity": 0.53, "pressure": 1018.31, "windSpeed": 4.2, "windGust": 15.5, "windGustTime": 1564203600, "windBearing": 81, "cloudCover": 0.09, "uvIndex": 10, "uvIndexTime": 1564167600, "visibility": 9.977, "ozone": 293.3, "temperatureMin": 62.1, "temperatureMinTime": 1564142400, "temperatureMax": 93.55, "temperatureMaxTime": 1564182000, "apparentTemperatureMin": 62.24, "apparentTemperatureMinTime": 1564142400, "apparentTemperatureMax": 93.55, "apparentTemperatureMaxTime": 1564182000}, {"time": 1564203600, "summary": "Partly cloudy throughout the day.", "icon": "clear-day", "sunriseTime": 1564228162, "sunsetTime": 1564277382, "moonPhase": 0.85, "precipIntensity": 0.0001, "precipIntensityMax": 0.0005, "precipIntensityMaxTime": 1564239600, "precipProbability": 0.01, "precipType": "rain", "temperatureHigh": 93.94, "temperatureHighTime": 1564268400, "temperatureLow": 73.62, "temperatureLowTime": 1564311600, "apparentTemperatureHigh": 94.05, "apparentTemperatureHighTime": 1564268400, "apparentTemperatureLow": 75.18, "apparentTemperatureLowTime": 1564311600, "dewPoint": 63.19, "humidity": 0.57, "pressure": 1018.11, "windSpeed": 5.23, "windGust": 19.48, "windGustTime": 1564290000, "windBearing": 126, "cloudCover": 0.14, "uvIndex": 11, "uvIndexTime": 1564250400, "visibility": 10, "ozone": 288.5, "temperatureMin": 67.78, "temperatureMinTime": 1564228800, "temperatureMax": 93.94, "temperatureMaxTime": 1564268400, "apparentTemperatureMin": 68.36, "apparentTemperatureMinTime": 1564228800, "apparentTemperatureMax": 94.05, "apparentTemperatureMaxTime": 1564268400}, {"time": 1564290000, "summary": "Humid and partly cloudy throughout the day.", "icon": "partly-cloudy-day", "sunriseTime": 1564314598, "sunsetTime": 1564363745, "moonPhase": 0.88, "precipIntensity": 0.0004, "precipIntensityMax": 0.0017, "precipIntensityMaxTime": 1564358400, "precipProbability": 0.03, "precipType": "rain", "temperatureHigh": 95.33, "temperatureHighTime": 1564347600, "temperatureLow": 74.99, "temperatureLowTime": 1564398000, "apparentTemperatureHigh": 98.82, "apparentTemperatureHighTime": 1564354800, "apparentTemperatureLow": 76.64, "apparentTemperatureLowTime": 1564398000, "dewPoint": 69.75, "humidity": 0.66, "pressure": 1016.11, "windSpeed": 9.22, "windGust": 27.85, "windGustTime": 1564372800, "windBearing": 161, "cloudCover": 0.26, "uvIndex": 11, "uvIndexTime": 1564336800, "visibility": 9.972, "ozone": 284.4, "temperatureMin": 73.62, "temperatureMinTime": 1564311600, "temperatureMax": 95.33, "temperatureMaxTime": 1564347600, "apparentTemperatureMin": 75.18, "apparentTemperatureMinTime": 1564311600, "apparentTemperatureMax": 98.82, "apparentTemperatureMaxTime": 1564354800}, {"time": 1564376400, "summary": "Humid and partly cloudy throughout the day.", "icon": "partly-cloudy-day", "sunriseTime": 1564401035, "sunsetTime": 1564450107, "moonPhase": 0.92, "precipIntensity": 0.0002, "precipIntensityMax": 0.0005, "precipIntensityMaxTime": 1564444800, "precipProbability": 0.02, "precipType": "rain", "temperatureHigh": 96.99, "temperatureHighTime": 1564441200, "temperatureLow": 73.46, "temperatureLowTime": 1564484400, "apparentTemperatureHigh": 99.14, "apparentTemperatureHighTime": 1564441200, "apparentTemperatureLow": 75.13, "apparentTemperatureLowTime": 1564484400, "dewPoint": 69.43, "humidity": 0.64, "pressure": 1014.77, "windSpeed": 9.44, "windGust": 27.02, "windGustTime": 1564376400, "windBearing": 166, "cloudCover": 0.38, "uvIndex": 10, "uvIndexTime": 1564426800, "visibility": 10, "ozone": 284.6, "temperatureMin": 74.99, "temperatureMinTime": 1564398000, "temperatureMax": 96.99, "temperatureMaxTime": 1564441200, "apparentTemperatureMin": 76.64, "apparentTemperatureMinTime": 1564398000, "apparentTemperatureMax": 99.14, "apparentTemperatureMaxTime": 1564441200}, {"time": 1564462800, "summary": "Humid and mostly cloudy throughout the day.", "icon": "partly-cloudy-day", "sunriseTime": 1564487471, "sunsetTime": 1564536467, "moonPhase": 0.96, "precipIntensity": 0.0014, "precipIntensityMax": 0.016, "precipIntensityMaxTime": 1564549200, "precipProbability": 0.08, "precipType": "rain", "temperatureHigh": 96.36, "temperatureHighTime": 1564527600, "temperatureLow": 75.56, "temperatureLowTime": 1564570800, "apparentTemperatureHigh": 97.23, "apparentTemperatureHighTime": 1564520400, "apparentTemperatureLow": 77.06, "apparentTemperatureLowTime": 1564570800, "dewPoint": 67.99, "humidity": 0.61, "pressure": 1014.98, "windSpeed": 7.72, "windGust": 25.19, "windGustTime": 1564542000, "windBearing": 173, "cloudCover": 0.54, "uvIndex": 8, "uvIndexTime": 1564516800, "visibility": 10, "ozone": 287.7, "temperatureMin": 73.46, "temperatureMinTime": 1564484400, "temperatureMax": 96.36, "temperatureMaxTime": 1564527600, "apparentTemperatureMin": 75.13, "apparentTemperatureMinTime": 1564484400, "apparentTemperatureMax": 97.23, "apparentTemperatureMaxTime": 1564520400}, {"time": 1564549200, "summary": "Humid and mostly cloudy throughout the day.", "icon": "partly-cloudy-day", "sunriseTime": 1564573908, "sunsetTime": 1564622826, "moonPhase": 1, "precipIntensity": 0.0049, "precipIntensityMax": 0.0182, "precipIntensityMaxTime": 1564552800, "precipProbability": 0.15, "precipType": "rain", "temperatureHigh": 93.85, "temperatureHighTime": 1564606800, "temperatureLow": 73.04, "temperatureLowTime": 1564660800, "apparentTemperatureHigh": 96.81, "apparentTemperatureHighTime": 1564603200, "apparentTemperatureLow": 74.49, "apparentTemperatureLowTime": 1564660800, "dewPoint": 69.29, "humidity": 0.64, "pressure": 1014.74, "windSpeed": 7.01, "windGust": 22.16, "windGustTime": 1564549200, "windBearing": 169, "cloudCover": 0.58, "uvIndex": 8, "uvIndexTime": 1564599600, "visibility": 10, "ozone": 290.4, "temperatureMin": 75.56, "temperatureMinTime": 1564570800, "temperatureMax": 93.85, "temperatureMaxTime": 1564606800, "apparentTemperatureMin": 77.06, "apparentTemperatureMinTime": 1564570800, "apparentTemperatureMax": 96.81, "apparentTemperatureMaxTime": 1564603200}, {"time": 1564635600, "summary": "Partly cloudy throughout the day.", "icon": "clear-day", "sunriseTime": 1564660344, "sunsetTime": 1564709184, "moonPhase": 0.04, "precipIntensity": 0.0013, "precipIntensityMax": 0.0121, "precipIntensityMaxTime": 1564635600, "precipProbability": 0.03, "precipType": "rain", "temperatureHigh": 94.83, "temperatureHighTime": 1564700400, "temperatureLow": 71.29, "temperatureLowTime": 1564747200, "apparentTemperatureHigh": 94.89, "apparentTemperatureHighTime": 1564700400, "apparentTemperatureLow": 72.67, "apparentTemperatureLowTime": 1564747200, "dewPoint": 66.1, "humidity": 0.59, "pressure": 1014.41, "windSpeed": 6.95, "windGust": 23.26, "windGustTime": 1564714800, "windBearing": 162, "cloudCover": 0.11, "uvIndex": 11, "uvIndexTime": 1564686000, "visibility": 10, "ozone": 293, "temperatureMin": 73.04, "temperatureMinTime": 1564660800, "temperatureMax": 94.83, "temperatureMaxTime": 1564700400, "apparentTemperatureMin": 74.49, "apparentTemperatureMinTime": 1564660800, "apparentTemperatureMax": 94.89, "apparentTemperatureMaxTime": 1564700400}, {"time": 1564722000, "summary": "Partly cloudy throughout the day.", "icon": "clear-day", "sunriseTime": 1564746781, "sunsetTime": 1564795541, "moonPhase": 0.08, "precipIntensity": 0, "precipIntensityMax": 0, "precipProbability": 0, "temperatureHigh": 95.77, "temperatureHighTime": 1564786800, "temperatureLow": 72.64, "temperatureLowTime": 1564830000, "apparentTemperatureHigh": 97.21, "apparentTemperatureHighTime": 1564786800, "apparentTemperatureLow": 74, "apparentTemperatureLowTime": 1564830000, "dewPoint": 66.16, "humidity": 0.58, "pressure": 1013.66, "windSpeed": 7.34, "windGust": 24.01, "windGustTime": 1564801200, "windBearing": 167, "cloudCover": 0.12, "uvIndex": 11, "uvIndexTime": 1564772400, "visibility": 10, "ozone": 292.3, "temperatureMin": 71.29, "temperatureMinTime": 1564747200, "temperatureMax": 95.77, "temperatureMaxTime": 1564786800, "apparentTemperatureMin": 72.67, "apparentTemperatureMinTime": 1564747200, "apparentTemperatureMax": 97.21, "apparentTemperatureMaxTime": 1564786800}]}, "alerts": [{"title": "Air Quality Alert", "regions": ["Bastrop", "Caldwell", "Hays", "Travis", "Williamson"], "severity": "advisory", "time": 1564081800, "expires": 1564272000, "description": "...OZONE ACTION DAY... The Texas Commission on Environmental Quality (TCEQ) has issued an Ozone Action Day for the Austin area for Saturday July 27th 2019. Atmospheric conditions are expected to be favorable for producing high levels of ozone air pollution in the Austin area on Saturday. You can help prevent ozone pollution by sharing a ride...walking or riding a bicycle...taking your lunch to work...avoiding drive through lanes...conserving energy...and keeping your vehicle properly tuned. If required...the next Air Pollution Watch will be issued by 3 PM on Saturday July 27th 2019. && For more information on ozone: OZONE...THE FACTS: www.tceq.texas.gov/airquality/monops/ozonefacts.html EPA AIR NOW: www.airnow.gov/index.cfm?action=airnow.local_state&stateid=45&tab=0 TAKE CARE OF TEXAS: www.takecareoftexas.org CAPITAL AREA COUNCIL OF GOVERNMENTS AIR QUALITY: www.capcog.org/divisions/regional-services/air-quality CLEAN AIR FORCE OF CENTRAL TEXAS: www.cleanairforce.org\n", "uri": "https://alerts.weather.gov/cap/wwacapget.php?x=TX125D050FE028.AirQualityAlert.125D052B9200TX.EWXAQAEWX.c0d41b83c0284ee9e1f04bad8a0ce307"}], "offset": -5}